nano_template/__init__.py
nano_template/__init__.pyi
nano_template/_exceptions.py
nano_template/_nano_template.cp314t-win_arm64.pyd
nano_template/_nano_template.pyi
nano_template/_pure.py
nano_template/_token_kind.py
nano_template/_undefined.py
nano_template/py.typed
nano_template-0.1.1.dist-info/licenses/LICENSE
nano_template-0.1.1.dist-info/METADATA
nano_template-0.1.1.dist-info/WHEEL
nano_template-0.1.1.dist-info/top_level.txt
nano_template-0.1.1.dist-info/RECORD
