Metadata-Version: 2.4
Name: nano-template
Version: 0.1.1
Summary: Minimal, fast templates for Python
Author-email: James Prior <jamesgr.prior@gmail.com>
License-Expression: MIT
Project-URL: Issues, https://github.com/jg-rp/nano-template/issues
Project-URL: Source, https://github.com/jg-rp/nano-template
Classifier: Development Status :: 4 - Beta
Classifier: Programming Language :: Python
Classifier: Programming Language :: Python :: 3.10
Classifier: Programming Language :: Python :: 3.11
Classifier: Programming Language :: Python :: 3.12
Classifier: Programming Language :: Python :: 3.13
Classifier: Programming Language :: Python :: 3.14
Classifier: Programming Language :: Python :: Implementation :: CPython
Requires-Python: >=3.10
License-File: LICENSE
Dynamic: license-file
